cdk_serverless_video_transcoder/__init__.py
cdk_serverless_video_transcoder/py.typed
cdk_serverless_video_transcoder/_jsii/__init__.py
cdk_serverless_video_transcoder/_jsii/cdk-serverless-video-transcoder@0.0.3.jsii.tgz
cdk_serverless_video_transcoder-0.0.3.dist-info/METADATA
cdk_serverless_video_transcoder-0.0.3.dist-info/WHEEL
cdk_serverless_video_transcoder-0.0.3.dist-info/top_level.txt
cdk_serverless_video_transcoder-0.0.3.dist-info/RECORD
